[
  {
    "design": "gcd_preroute",
    "pdk": "nangate45",
    "N": 357,
    "N_total": 357,
    "m_rows": 42,
    "cell_aspect": 1.8421052631578947,
    "sweep": [
      {
        "r": 1.1199999999999999,
        "nE": 48,
        "nE_intra": 48,
        "nE_inter": 0,
        "c": 309,
        "dbar": 0.2689075630252101,
        "rank_theorem_G": 48,
        "rank_actual": 48,
        "rank_error": 0,
        "eta_row": 0.0,
        "eta_generic": 0.0,
        "eta_actual": 0.0,
        "gap_predicted": 13.875,
        "gap_actual": 0.0,
        "nv_eff": 0.13445378151260504,
        "f_intra": 1.0
      },
      {
        "r": 1.1400000000000001,
        "nE": 49,
        "nE_intra": 49,
        "nE_inter": 0,
        "c": 308,
        "dbar": 0.27450980392156865,
        "rank_theorem_G": 49,
        "rank_actual": 49,
        "rank_error": 0,
        "eta_row": 0.0,
        "eta_generic": 0.0,
        "eta_actual": 0.0,
        "gap_predicted": 13.571428571428571,
        "gap_actual": 0.0,
        "nv_eff": 0.13725490196078433,
        "f_intra": 1.0
      },
      {
        "r": 1.4,
        "nE": 93,
        "nE_intra": 82,
        "nE_inter": 11,
        "c": 275,
        "dbar": 0.5210084033613446,
        "rank_theorem_G": 93,
        "rank_actual": 93,
        "rank_error": 0,
        "eta_row": 0.0,
        "eta_generic": 0.0,
        "eta_actual": 0.0,
        "gap_predicted": 6.67741935483871,
        "gap_actual": 0.0,
        "nv_eff": 0.2605042016806723,
        "f_intra": 0.8817204301075269
      },
      {
        "r": 1.52,
        "nE": 209,
        "nE_intra": 89,
        "nE_inter": 120,
        "c": 268,
        "dbar": 1.1708683473389356,
        "rank_theorem_G": 209,
        "rank_actual": 209,
        "rank_error": 0,
        "eta_row": 0.0,
        "eta_generic": 0.0,
        "eta_actual": 0.0,
        "gap_predicted": 2.416267942583732,
        "gap_actual": 0.0,
        "nv_eff": 0.5854341736694678,
        "f_intra": 0.4258373205741627
      },
      {
        "r": 1.68,
        "nE": 276,
        "nE_intra": 97,
        "nE_inter": 179,
        "c": 260,
        "dbar": 1.546218487394958,
        "rank_theorem_G": 276,
        "rank_actual": 276,
        "rank_error": 0,
        "eta_row": 0.0,
        "eta_generic": 0.0,
        "eta_actual": 0.0,
        "gap_predicted": 1.5869565217391304,
        "gap_actual": 0.0,
        "nv_eff": 0.773109243697479,
        "f_intra": 0.35144927536231885
      },
      {
        "r": 2.0999999999999996,
        "nE": 407,
        "nE_intra": 126,
        "nE_inter": 281,
        "c": 234,
        "dbar": 2.280112044817927,
        "rank_theorem_G": 404,
        "rank_actual": 404,
        "rank_error": 0,
        "eta_row": 0.0073710073710073765,
        "eta_generic": 0.0,
        "eta_actual": 0.007371007371007371,
        "gap_predicted": 0.7616707616707616,
        "gap_actual": 0.007371007371007371,
        "nv_eff": 1.1316526610644257,
        "f_intra": 0.3095823095823096
      },
      {
        "r": 2.2800000000000002,
        "nE": 441,
        "nE_intra": 141,
        "nE_inter": 300,
        "c": 225,
        "dbar": 2.4705882352941178,
        "rank_theorem_G": 432,
        "rank_actual": 436,
        "rank_error": 4,
        "eta_row": 0.020408163265306145,
        "eta_generic": 0.0,
        "eta_actual": 0.011337868480725623,
        "gap_predicted": 0.6394557823129252,
        "gap_actual": 0.011337868480725623,
        "nv_eff": 1.2100840336134453,
        "f_intra": 0.3197278911564626
      },
      {
        "r": 2.8,
        "nE": 587,
        "nE_intra": 193,
        "nE_inter": 394,
        "c": 192,
        "dbar": 3.288515406162465,
        "rank_theorem_G": 559,
        "rank_actual": 544,
        "rank_error": -15,
        "eta_row": 0.047700170357751315,
        "eta_generic": 0.0,
        "eta_actual": 0.07325383304940375,
        "gap_predicted": 0.26405451448040884,
        "gap_actual": 0.07325383304940375,
        "nv_eff": 1.5658263305322129,
        "f_intra": 0.3287904599659284
      },
      {
        "r": 3.1859692402783804,
        "nE": 870,
        "nE_intra": 215,
        "nE_inter": 655,
        "c": 179,
        "dbar": 4.873949579831932,
        "rank_theorem_G": 714,
        "rank_actual": 675,
        "rank_error": -39,
        "eta_row": 0.17931034482758623,
        "eta_generic": 0.17931034482758623,
        "eta_actual": 0.22413793103448276,
        "gap_predicted": 0.0,
        "gap_actual": 0.04482758620689653,
        "nv_eff": 2.0,
        "f_intra": 0.2471264367816092
      },
      {
        "r": 4.199999999999999,
        "nE": 1219,
        "nE_intra": 272,
        "nE_inter": 947,
        "c": 158,
        "dbar": 6.829131652661064,
        "rank_theorem_G": 714,
        "rank_actual": 690,
        "rank_error": -24,
        "eta_row": 0.4142739950779327,
        "eta_generic": 0.4142739950779327,
        "eta_actual": 0.4339622641509434,
        "gap_predicted": 0.0,
        "gap_actual": 0.01968826907301069,
        "nv_eff": 2.0,
        "f_intra": 0.22313371616078753
      },
      {
        "r": 4.7789538604175705,
        "nE": 1592,
        "nE_intra": 293,
        "nE_inter": 1299,
        "c": 150,
        "dbar": 8.918767507002801,
        "rank_theorem_G": 714,
        "rank_actual": 693,
        "rank_error": -21,
        "eta_row": 0.5515075376884422,
        "eta_generic": 0.5515075376884422,
        "eta_actual": 0.5646984924623115,
        "gap_predicted": 0.0,
        "gap_actual": 0.013190954773869334,
        "nv_eff": 2.0,
        "f_intra": 0.18404522613065327
      },
      {
        "r": 7.964923100695951,
        "nE": 3683,
        "nE_intra": 462,
        "nE_inter": 3221,
        "c": 106,
        "dbar": 20.633053221288517,
        "rank_theorem_G": 714,
        "rank_actual": 698,
        "rank_error": -16,
        "eta_row": 0.8061363019277763,
        "eta_generic": 0.8061363019277763,
        "eta_actual": 0.8104805864784144,
        "gap_predicted": 0.0,
        "gap_actual": 0.004344284550638067,
        "nv_eff": 2.0,
        "f_intra": 0.12544121639967418
      },
      {
        "r": 15.929846201391902,
        "nE": 13809,
        "nE_intra": 881,
        "nE_inter": 12928,
        "c": 61,
        "dbar": 77.36134453781513,
        "rank_theorem_G": 714,
        "rank_actual": 706,
        "rank_error": -8,
        "eta_row": 0.9482945904844666,
        "eta_generic": 0.9482945904844666,
        "eta_actual": 0.9488739228039684,
        "gap_predicted": 0.0,
        "gap_actual": 0.0005793323195018019,
        "nv_eff": 2.0,
        "f_intra": 0.06379897168513289
      }
    ]
  },
  {
    "design": "gcd_sky130",
    "pdk": "sky130hd",
    "N": 370,
    "N_total": 370,
    "m_rows": 68,
    "cell_aspect": 0.84472049689441,
    "sweep": [
      {
        "r": 2.72,
        "nE": 6,
        "nE_intra": 0,
        "nE_inter": 6,
        "c": 370,
        "dbar": 0.032432432432432434,
        "rank_theorem_G": 6,
        "rank_actual": 6,
        "rank_error": 0,
        "eta_row": 0.0,
        "eta_generic": 0.0,
        "eta_actual": 0.0,
        "gap_predicted": 122.33333333333333,
        "gap_actual": 0.0,
        "nv_eff": 0.016216216216216217,
        "f_intra": 0.0
      },
      {
        "r": 3.22,
        "nE": 82,
        "nE_intra": 3,
        "nE_inter": 79,
        "c": 367,
        "dbar": 0.44324324324324327,
        "rank_theorem_G": 82,
        "rank_actual": 82,
        "rank_error": 0,
        "eta_row": 0.0,
        "eta_generic": 0.0,
        "eta_actual": 0.0,
        "gap_predicted": 8.024390243902438,
        "gap_actual": 0.0,
        "nv_eff": 0.22162162162162163,
        "f_intra": 0.036585365853658534
      },
      {
        "r": 3.2640000000000002,
        "nE": 84,
        "nE_intra": 5,
        "nE_inter": 79,
        "c": 365,
        "dbar": 0.4540540540540541,
        "rank_theorem_G": 84,
        "rank_actual": 84,
        "rank_error": 0,
        "eta_row": 0.0,
        "eta_generic": 0.0,
        "eta_actual": 0.0,
        "gap_predicted": 7.809523809523809,
        "gap_actual": 0.0,
        "nv_eff": 0.22702702702702704,
        "f_intra": 0.05952380952380952
      },
      {
        "r": 4.08,
        "nE": 137,
        "nE_intra": 11,
        "nE_inter": 126,
        "c": 359,
        "dbar": 0.7405405405405405,
        "rank_theorem_G": 137,
        "rank_actual": 137,
        "rank_error": 0,
        "eta_row": 0.0,
        "eta_generic": 0.0,
        "eta_actual": 0.0,
        "gap_predicted": 4.401459854014599,
        "gap_actual": 0.0,
        "nv_eff": 0.37027027027027026,
        "f_intra": 0.08029197080291971
      },
      {
        "r": 4.83,
        "nE": 186,
        "nE_intra": 28,
        "nE_inter": 158,
        "c": 342,
        "dbar": 1.0054054054054054,
        "rank_theorem_G": 186,
        "rank_actual": 186,
        "rank_error": 0,
        "eta_row": 0.0,
        "eta_generic": 0.0,
        "eta_actual": 0.0,
        "gap_predicted": 2.978494623655914,
        "gap_actual": 0.0,
        "nv_eff": 0.5027027027027027,
        "f_intra": 0.15053763440860216
      },
      {
        "r": 5.44,
        "nE": 244,
        "nE_intra": 38,
        "nE_inter": 206,
        "c": 332,
        "dbar": 1.318918918918919,
        "rank_theorem_G": 244,
        "rank_actual": 244,
        "rank_error": 0,
        "eta_row": 0.0,
        "eta_generic": 0.0,
        "eta_actual": 0.0,
        "gap_predicted": 2.0327868852459017,
        "gap_actual": 0.0,
        "nv_eff": 0.6594594594594595,
        "f_intra": 0.1557377049180328
      },
      {
        "r": 6.44,
        "nE": 453,
        "nE_intra": 64,
        "nE_inter": 389,
        "c": 306,
        "dbar": 2.4486486486486485,
        "rank_theorem_G": 453,
        "rank_actual": 392,
        "rank_error": -61,
        "eta_row": 0.0,
        "eta_generic": 0.0,
        "eta_actual": 0.1346578366445916,
        "gap_predicted": 0.6335540838852097,
        "gap_actual": 0.1346578366445916,
        "nv_eff": 1.2243243243243243,
        "f_intra": 0.141280353200883
      },
      {
        "r": 8.16,
        "nE": 634,
        "nE_intra": 93,
        "nE_inter": 541,
        "c": 279,
        "dbar": 3.427027027027027,
        "rank_theorem_G": 632,
        "rank_actual": 445,
        "rank_error": -187,
        "eta_row": 0.003154574132492094,
        "eta_generic": 0.0,
        "eta_actual": 0.2981072555205047,
        "gap_predicted": 0.17034700315457413,
        "gap_actual": 0.2981072555205047,
        "nv_eff": 1.7081081081081082,
        "f_intra": 0.14668769716088328
      },
      {
        "r": 8.430136416452584,
        "nE": 733,
        "nE_intra": 99,
        "nE_inter": 634,
        "c": 274,
        "dbar": 3.962162162162162,
        "rank_theorem_G": 730,
        "rank_actual": 466,
        "rank_error": -264,
        "eta_row": 0.004092769440654842,
        "eta_generic": 0.0,
        "eta_actual": 0.36425648021828105,
        "gap_predicted": 0.013642564802182811,
        "gap_actual": 0.36425648021828105,
        "nv_eff": 1.972972972972973,
        "f_intra": 0.13506139154160982
      },
      {
        "r": 9.66,
        "nE": 966,
        "nE_intra": 128,
        "nE_inter": 838,
        "c": 252,
        "dbar": 5.221621621621622,
        "rank_theorem_G": 740,
        "rank_actual": 509,
        "rank_error": -231,
        "eta_row": 0.23395445134575565,
        "eta_generic": 0.23395445134575565,
        "eta_actual": 0.4730848861283644,
        "gap_predicted": 0.0,
        "gap_actual": 0.23913043478260876,
        "nv_eff": 2.0,
        "f_intra": 0.13250517598343686
      },
      {
        "r": 12.645204624678875,
        "nE": 1626,
        "nE_intra": 186,
        "nE_inter": 1440,
        "c": 215,
        "dbar": 8.78918918918919,
        "rank_theorem_G": 740,
        "rank_actual": 588,
        "rank_error": -152,
        "eta_row": 0.5448954489544895,
        "eta_generic": 0.5448954489544895,
        "eta_actual": 0.6383763837638377,
        "gap_predicted": 0.0,
        "gap_actual": 0.09348093480934816,
        "nv_eff": 2.0,
        "f_intra": 0.11439114391143912
      },
      {
        "r": 21.07534104113146,
        "nE": 4295,
        "nE_intra": 331,
        "nE_inter": 3964,
        "c": 167,
        "dbar": 23.216216216216218,
        "rank_theorem_G": 740,
        "rank_actual": 695,
        "rank_error": -45,
        "eta_row": 0.8277066356228172,
        "eta_generic": 0.8277066356228172,
        "eta_actual": 0.8381839348079162,
        "gap_predicted": 0.0,
        "gap_actual": 0.010477299185098987,
        "nv_eff": 2.0,
        "f_intra": 0.07706635622817229
      },
      {
        "r": 42.15068208226292,
        "nE": 13954,
        "nE_intra": 640,
        "nE_inter": 13314,
        "c": 125,
        "dbar": 75.42702702702702,
        "rank_theorem_G": 740,
        "rank_actual": 734,
        "rank_error": -6,
        "eta_row": 0.9469686111509245,
        "eta_generic": 0.9469686111509245,
        "eta_actual": 0.9473985953848358,
        "gap_predicted": 0.0,
        "gap_actual": 0.00042998423391138463,
        "nv_eff": 2.0,
        "f_intra": 0.045864984950551815
      }
    ]
  },
  {
    "design": "aes_preroute",
    "pdk": "nangate45",
    "N": 1500,
    "N_total": 16591,
    "m_rows": 85,
    "cell_aspect": 1.3397129186602872,
    "sweep": [
      {
        "r": 1.045,
        "nE": 49,
        "nE_intra": 49,
        "nE_inter": 0,
        "c": 1451,
        "dbar": 0.06533333333333333,
        "rank_theorem_G": 49,
        "rank_actual": 49,
        "rank_error": 0,
        "eta_row": 0.0,
        "eta_generic": 0.0,
        "eta_actual": 0.0,
        "gap_predicted": 60.224489795918366,
        "gap_actual": 0.0,
        "nv_eff": 0.03266666666666666,
        "f_intra": 1.0
      },
      {
        "r": 1.1199999999999999,
        "nE": 69,
        "nE_intra": 69,
        "nE_inter": 0,
        "c": 1431,
        "dbar": 0.092,
        "rank_theorem_G": 69,
        "rank_actual": 69,
        "rank_error": 0,
        "eta_row": 0.0,
        "eta_generic": 0.0,
        "eta_actual": 0.0,
        "gap_predicted": 42.47826086956522,
        "gap_actual": 0.0,
        "nv_eff": 0.046,
        "f_intra": 1.0
      },
      {
        "r": 1.4,
        "nE": 203,
        "nE_intra": 190,
        "nE_inter": 13,
        "c": 1310,
        "dbar": 0.27066666666666667,
        "rank_theorem_G": 203,
        "rank_actual": 203,
        "rank_error": 0,
        "eta_row": 0.0,
        "eta_generic": 0.0,
        "eta_actual": 0.0,
        "gap_predicted": 13.77832512315271,
        "gap_actual": 0.0,
        "nv_eff": 0.13533333333333333,
        "f_intra": 0.9359605911330049
      },
      {
        "r": 1.5675,
        "nE": 736,
        "nE_intra": 263,
        "nE_inter": 473,
        "c": 1237,
        "dbar": 0.9813333333333333,
        "rank_theorem_G": 736,
        "rank_actual": 736,
        "rank_error": 0,
        "eta_row": 0.0,
        "eta_generic": 0.0,
        "eta_actual": 0.0,
        "gap_predicted": 3.0760869565217392,
        "gap_actual": 0.0,
        "nv_eff": 0.49066666666666664,
        "f_intra": 0.35733695652173914
      },
      {
        "r": 1.68,
        "nE": 910,
        "nE_intra": 294,
        "nE_inter": 616,
        "c": 1206,
        "dbar": 1.2133333333333334,
        "rank_theorem_G": 910,
        "rank_actual": 910,
        "rank_error": 0,
        "eta_row": 0.0,
        "eta_generic": 0.0,
        "eta_actual": 0.0,
        "gap_predicted": 2.2967032967032965,
        "gap_actual": 0.0,
        "nv_eff": 0.6066666666666667,
        "f_intra": 0.3230769230769231
      },
      {
        "r": 2.09,
        "nE": 1448,
        "nE_intra": 432,
        "nE_inter": 1016,
        "c": 1072,
        "dbar": 1.9306666666666668,
        "rank_theorem_G": 1444,
        "rank_actual": 1443,
        "rank_error": -1,
        "eta_row": 0.002762430939226568,
        "eta_generic": 0.0,
        "eta_actual": 0.003453038674033149,
        "gap_predicted": 1.074585635359116,
        "gap_actual": 0.003453038674033149,
        "nv_eff": 0.9626666666666667,
        "f_intra": 0.2983425414364641
      },
      {
        "r": 2.0999999999999996,
        "nE": 1469,
        "nE_intra": 453,
        "nE_inter": 1016,
        "c": 1052,
        "dbar": 1.9586666666666666,
        "rank_theorem_G": 1464,
        "rank_actual": 1463,
        "rank_error": -1,
        "eta_row": 0.003403675970047648,
        "eta_generic": 0.0,
        "eta_actual": 0.0040844111640571815,
        "gap_predicted": 1.0456092579986385,
        "gap_actual": 0.0040844111640571815,
        "nv_eff": 0.976,
        "f_intra": 0.30837304288631723
      },
      {
        "r": 2.8,
        "nE": 2112,
        "nE_intra": 637,
        "nE_inter": 1475,
        "c": 933,
        "dbar": 2.816,
        "rank_theorem_G": 2042,
        "rank_actual": 2032,
        "rank_error": -10,
        "eta_row": 0.03314393939393945,
        "eta_generic": 0.0,
        "eta_actual": 0.03787878787878788,
        "gap_predicted": 0.45359848484848486,
        "gap_actual": 0.03787878787878788,
        "nv_eff": 1.3613333333333333,
        "f_intra": 0.3016098484848485
      },
      {
        "r": 3.135,
        "nE": 3060,
        "nE_intra": 728,
        "nE_inter": 2332,
        "c": 874,
        "dbar": 4.08,
        "rank_theorem_G": 2958,
        "rank_actual": 2629,
        "rank_error": -329,
        "eta_row": 0.033333333333333326,
        "eta_generic": 0.019607843137254943,
        "eta_actual": 0.14084967320261438,
        "gap_predicted": 0.013725490196078431,
        "gap_actual": 0.12124183006535943,
        "nv_eff": 1.972,
        "f_intra": 0.23790849673202613
      },
      {
        "r": 3.4940091585455235,
        "nE": 3678,
        "nE_intra": 812,
        "nE_inter": 2866,
        "c": 825,
        "dbar": 4.904,
        "rank_theorem_G": 3000,
        "rank_actual": 2810,
        "rank_error": -190,
        "eta_row": 0.18433931484502442,
        "eta_generic": 0.18433931484502442,
        "eta_actual": 0.2359978249048396,
        "gap_predicted": 0.0,
        "gap_actual": 0.05165851005981517,
        "nv_eff": 2.0,
        "f_intra": 0.2207721587819467
      },
      {
        "r": 4.199999999999999,
        "nE": 4688,
        "nE_intra": 1002,
        "nE_inter": 3686,
        "c": 713,
        "dbar": 6.250666666666667,
        "rank_theorem_G": 3000,
        "rank_actual": 2939,
        "rank_error": -61,
        "eta_row": 0.36006825938566556,
        "eta_generic": 0.36006825938566556,
        "eta_actual": 0.373080204778157,
        "gap_predicted": 0.0,
        "gap_actual": 0.013011945392491453,
        "nv_eff": 2.0,
        "f_intra": 0.2137372013651877
      },
      {
        "r": 5.241013737818285,
        "nE": 7706,
        "nE_intra": 1287,
        "nE_inter": 6419,
        "c": 588,
        "dbar": 10.274666666666667,
        "rank_theorem_G": 3000,
        "rank_actual": 3000,
        "rank_error": 0,
        "eta_row": 0.6106929665195951,
        "eta_generic": 0.6106929665195951,
        "eta_actual": 0.6106929665195951,
        "gap_predicted": 0.0,
        "gap_actual": 0.0,
        "nv_eff": 2.0,
        "f_intra": 0.1670127173630937
      },
      {
        "r": 8.735022896363809,
        "nE": 23177,
        "nE_intra": 2320,
        "nE_inter": 20857,
        "c": 289,
        "dbar": 30.902666666666665,
        "rank_theorem_G": 3000,
        "rank_actual": 3000,
        "rank_error": 0,
        "eta_row": 0.8705613323553523,
        "eta_generic": 0.8705613323553523,
        "eta_actual": 0.8705613323553523,
        "gap_predicted": 0.0,
        "gap_actual": 0.0,
        "nv_eff": 2.0,
        "f_intra": 0.10009923631186089
      }
    ]
  }
]